mip2scout/__init__.py
mip2scout/automate.py
mip2scout/constants.py
mip2scout/coverage.py
mip2scout/exc.py
mip2scout/frequency.py
mip2scout/info.py
mip2scout/log.py
mip2scout/madeline.py
mip2scout/scout_tools.py
mip2scout/cli/__init__.py
mip2scout/cli/do.py
mip2scout/cli/root.py
mip2scout/cli/scout.py
mip2scout/cli/status.py
mip2scout/cli/utils.py
mip2scout-0.1.4.dist-info/DESCRIPTION.rst
mip2scout-0.1.4.dist-info/METADATA
mip2scout-0.1.4.dist-info/RECORD
mip2scout-0.1.4.dist-info/WHEEL
mip2scout-0.1.4.dist-info/entry_points.txt
mip2scout-0.1.4.dist-info/metadata.json
mip2scout-0.1.4.dist-info/top_level.txt
