Metadata-Version: 2.0
Name: mip2scout
Version: 0.1.4
Summary: Microservice :)
Home-page: UNKNOWN
Author: Robin Andeer
Author-email: robin.andeer@scilifelab.se
License: BSD License
Keywords: pytest flask
Platform: any
Classifier: Development Status :: 3 - Alpha
Classifier: License :: OSI Approved :: BSD License
Classifier: Operating System :: OS Independent
Classifier: Programming Language :: Python
Classifier: Programming Language :: Python :: 2
Classifier: Programming Language :: Python :: 2.7
Classifier: Programming Language :: Python :: 3
Classifier: Programming Language :: Python :: 3.3
Requires-Dist: Flask
Requires-Dist: PyOpenSSL
Requires-Dist: PyYAML
Requires-Dist: SQLAlchemy (>=0.8.2)
Requires-Dist: cffi
Requires-Dist: chanjo (>=3.4.0)
Requires-Dist: click
Requires-Dist: configobj
Requires-Dist: dataset
Requires-Dist: loqusdb
Requires-Dist: lxml (>=3.0)
Requires-Dist: path.py
Requires-Dist: pymip (>=0.1.2)
Requires-Dist: pymip (>=0.2.0)
Requires-Dist: pysam
Requires-Dist: scout-browser
Requires-Dist: six
Requires-Dist: taboo (>=0.6.1)
Requires-Dist: tabulate
